xoak/__init__.py
xoak/accessor.py
xoak/index/__init__.py
xoak/index/base.py
xoak/index/s2_adapters.py
xoak/index/scipy_adapters.py
xoak/index/sklearn_adapters.py
xoak/tests/__init__.py
xoak/tests/conftest.py
xoak/tests/test_accessor.py
xoak/tests/test_index_base.py
xoak/tests/test_s2_adapters.py
xoak/tests/test_scipy_adapters.py
xoak/tests/test_sklearn_adapters.py
xoak-0.1.1.dist-info/LICENSE
xoak-0.1.1.dist-info/METADATA
xoak-0.1.1.dist-info/WHEEL
xoak-0.1.1.dist-info/top_level.txt
xoak-0.1.1.dist-info/RECORD
