Metadata-Version: 2.1
Name: xoak
Version: 0.1.1
Summary: Xarray extension that provides indexes for selecting irregular, n-dimensional data.
Home-page: https://github.com/xarray-contrib/xoak
Maintainer: Benoit Bovy, Willi Rath
Maintainer-email: benbovy@gmail.com
License: MIT
Keywords: xarray,index
Platform: UNKNOWN
Classifier: Development Status :: 3 - Alpha
Classifier: License :: OSI Approved :: MIT License
Classifier: Operating System :: OS Independent
Classifier: Intended Audience :: Science/Research
Classifier: Programming Language :: Python
Classifier: Programming Language :: Python :: 3
Classifier: Programming Language :: Python :: 3.6
Classifier: Programming Language :: Python :: 3.7
Classifier: Programming Language :: Python :: 3.8
Classifier: Programming Language :: Python :: 3.9
Classifier: Topic :: Scientific/Engineering
Requires-Python: >=3.6
Requires-Dist: xarray
Requires-Dist: numpy
Requires-Dist: dask
Requires-Dist: scipy
Provides-Extra: dev
Requires-Dist: scikit-learn ; extra == 'dev'
Requires-Dist: pytest ; extra == 'dev'
Requires-Dist: pytest-cov ; extra == 'dev'
Requires-Dist: pre-commit ; extra == 'dev'
